biowave/__init__.py
biowave-0.0.2.dist-info/LICENSE
biowave-0.0.2.dist-info/METADATA
biowave-0.0.2.dist-info/WHEEL
biowave-0.0.2.dist-info/top_level.txt
biowave-0.0.2.dist-info/RECORD
