Metadata-Version: 2.1
Name: biowave
Version: 0.0.2
Summary: Biosignal wrapper pipeline
Home-page: https://github.com/faruqsandi/biowave
Author: Faruq Sandi
Author-email: alice@example.com
License: UNKNOWN
Platform: UNKNOWN
Classifier: Programming Language :: Python :: 3
Classifier: License :: OSI Approved :: MIT License
Classifier: Operating System :: OS Independent
Requires-Python: >=3.6
